thespiae/__init__.py
thespiae/__main__.py
thespiae/cli.py
thespiae/core.py
thespiae/exception.py
thespiae/conf/__init__.py
thespiae/conf/core.py
thespiae/conf/data.py
thespiae/conf/exception.py
thespiae/conf/singleton.py
thespiae/conf/system.py
thespiae/install/__init__.py
thespiae/install/core.py
thespiae/install/data.py
thespiae/install/exception.py
thespiae/install/protocol.py
thespiae/install/singleton.py
thespiae/install/system.py
thespiae/path/__init__.py
thespiae/path/core.py
thespiae/path/exception.py
thespiae/path/factory.py
thespiae/path/protocol.py
thespiae/path/singleton.py
thespiae/path/system.py
thespiae/path/envparse/EnvLexer.py
thespiae/path/envparse/EnvParser.py
thespiae/path/envparse/EnvParserListener.py
thespiae/path/envparse/__init__.py
thespiae-0.1.dist-info/LICENSE
thespiae-0.1.dist-info/METADATA
thespiae-0.1.dist-info/WHEEL
thespiae-0.1.dist-info/entry_points.txt
thespiae-0.1.dist-info/top_level.txt
thespiae-0.1.dist-info/RECORD
