Metadata-Version: 2.1
Name: thespiae
Version: 0.1
Summary: Tool to setup Windows-based development environments
Home-page: https://github.com/apleshakov/thespiae
Author: Andrey Pleshakov
Author-email: aplshkv@gmail.com
License: Apache-2.0
Platform: UNKNOWN
Classifier: Environment :: Console
Classifier: License :: OSI Approved :: Apache Software License
Classifier: Natural Language :: English
Classifier: Operating System :: Microsoft :: Windows
Classifier: Programming Language :: Python :: 3.8
Classifier: Topic :: Utilities
Requires-Python: >=3.8.1
Requires-Dist: antlr4-python3-runtime (~=4.7.2)
Requires-Dist: pyyaml (>=5.1)
Requires-Dist: aiohttp (>=3.6.2)
Requires-Dist: tqdm (>=4.31.1)
Requires-Dist: colorama (~=0.4.1)
